verilog/adc_spi_slave_demo.v
/*
 * Module: adc_spi_slave
 * Date: Saturday, October 11, 2025
 *
 * Description:
 * A robust, fully synchronous SPI slave module with a clear separation
 * between the state machine logic and the datapath logic. It safely handles
 * the asynchronous 'sck' signal by synchronizing it to the main system 'clk'
 * and using edge-detect pulses to drive the logic. This version is optimized
 * to remove dedicated command and address registers and uses an explicit
 * MSB-first bit mapping for clarity.
 *
 * SPI Protocol:
 * - 16-bit transaction length
 * - Frame: [CMD(2 bits), ADDR(2 bits), DATA(12 bits)]
 * - SPI Mode 0 compatible (data shifted in on rising SCK, shifted out on falling SCK)
 */
module adc_spi_slave (
    // System Interface
    input           clk,     // Main system clock
    input           reset_,  // Active-low asynchronous reset

    // SPI Interface
    input           cs,      // Chip Select (active-low)
    input           sck,     // SPI Clock from Master
    input           mosi,    // Master Out, Slave In
    output          miso     // Master In, Slave Out
);

//=============================================================================
// Parameters
//=============================================================================

// State Definitions
localparam S_IDLE  = 2'b00;
localparam S_SHIFT = 2'b01;
localparam S_LATCH = 2'b11;

// Command Definitions
localparam READ    = 2'b00;
localparam WRITE   = 2'b01;
localparam SET     = 2'b10;
localparam CLEAR   = 2'b11;

// Address Definitions
localparam ADDR_CTRL_REG   = 2'b00;
localparam ADDR_STATUS_REG = 2'b01;
localparam ADDR_DATA_REG   = 2'b10;
localparam ADDR_OFFSET_REG = 2'b11;


//=============================================================================
// Internal Registers & Wires
//=============================================================================

// Slave Data Registers
reg [11:0] ctrl_reg;    // R/W
reg [11:0] status_reg;  // R-Only
reg [11:0] data_reg;    // R-Only
reg [11:0] offset_reg;  // R-Only

// State Machine
reg [1:0]  state_reg, next_state;

// Transactional Logic
reg [4:0]  counter;
reg [15:0] shift_reg;
reg [11:0] miso_data_buffer;

// SCK Synchronizer & Edge Detector
reg  sck_sync1, sck_sync2;
wire posedge_sck_pulse;
wire negedge_sck_pulse;

// Readable aliases for command, address, and data payloads
wire [1:0]  cmd_buffer;
wire [1:0]  addr_buffer;
wire [11:0] mosi_data_buffer;


//=============================================================================
// Continuous Assignments
//=============================================================================

assign cmd_buffer       = shift_reg[15:14];
assign addr_buffer      = shift_reg[13:12];
assign mosi_data_buffer = shift_reg[11:0];
assign miso             = cs ? 1'bz : miso_data_buffer[11];


//=============================================================================
// SCK Synchronizer and Edge Detector
//=============================================================================

always @(posedge clk or negedge reset_) begin
    if (!reset_) begin
        sck_sync1 <= 1'b0;
        sck_sync2 <= 1'b0;
    end
    else begin
        sck_sync1 <= sck;
        sck_sync2 <= sck_sync1;
    end
end

assign posedge_sck_pulse = ~sck_sync2 &  sck_sync1;
assign negedge_sck_pulse =  sck_sync2 & ~sck_sync1;


//=============================================================================
// State Logic
//=============================================================================

// 1. State Register (Sequential): This block holds the current state.
always @(posedge clk or negedge reset_) begin
    if (!reset_) begin
        state_reg <= S_IDLE;
    end
    else begin
        state_reg <= next_state;
    end
end

// 2. Next-State Logic (Combinational): This block determines the next state
// based on the current state and inputs.
always @(*) begin
    next_state = state_reg; // Default: stay in the current state
    case (state_reg)
        S_IDLE: begin
            if (!cs) begin
                next_state = S_SHIFT;
            end
        end
        S_SHIFT: begin
            if (cs || counter == 5'd16) begin
                next_state = S_LATCH;
            end
        end
        S_LATCH: begin
            if (cs) begin
                next_state = S_IDLE;
            end else begin
                next_state = S_SHIFT; // For back-to-back transactions
            end
        end
        default: begin
            next_state = S_IDLE;
        end
    endcase
end


//=============================================================================
// Datapath Logic (Sequential)
//=============================================================================

// This block handles all data manipulation, driven by the current state.
always @(posedge clk or negedge reset_) begin
    if (!reset_) begin
        // Asynchronous Reset for Datapath Registers
        counter          <= 5'b0;
        shift_reg        <= 16'b0;
        miso_data_buffer <= 12'b0;

        ctrl_reg         <= 12'h0;
        status_reg       <= 12'h800;
        data_reg         <= 12'h0;
        offset_reg       <= 12'h0;
    end
    else begin
        // Actions based on the current state
        case (state_reg)
            S_IDLE: begin
                // No actions needed here; counter reset happens in S_LATCH.
            end

            S_SHIFT: begin
                // Shift in data on the rising edge using explicit MSB-first mapping.
                if (posedge_sck_pulse && counter < 16) begin
                    shift_reg[15 - counter] <= mosi; // First bit goes to shift_reg[15]
                    counter                 <= counter + 1;
                end

                // Use if-else if structure to remove ambiguity
                if (counter == 4) begin
                    if (cmd_buffer == READ) begin
                       case (addr_buffer)
                            ADDR_CTRL_REG:   miso_data_buffer <= ctrl_reg;
                            ADDR_STATUS_REG: miso_data_buffer <= status_reg;
                            ADDR_DATA_REG:   miso_data_buffer <= data_reg;
                            ADDR_OFFSET_REG: miso_data_buffer <= offset_reg;
                            default:         miso_data_buffer <= 12'hBAD;
                       endcase
                    end
                end else if (counter > 4) begin
                    // For subsequent bits, shift the buffer left.
                    if (negedge_sck_pulse) begin
                        miso_data_buffer <= {miso_data_buffer[10:0], 1'b0};
                    end
                end
            end

            S_LATCH: begin
                // Perform register writes synchronously.
                if (counter == 16) begin
                    // Use the final position of the cmd/addr bits in shift_reg.
                    if (addr_buffer == ADDR_CTRL_REG) begin
                        case (cmd_buffer)
                            WRITE: ctrl_reg <= mosi_data_buffer;
                            SET:   ctrl_reg <= ctrl_reg | mosi_data_buffer;
                            CLEAR: ctrl_reg <= ctrl_reg & ~mosi_data_buffer;
                        endcase
                    end
                end

                // Reset the counter for the next transaction.
                counter <= 5'b0;
            end
        endcase
    end
end

endmodule

iverilog/testbench/tb_adc_spi_slave.v
//////////////////////////////////////////////////////////////////////////////////
//
// Module:       tb_adc_spi_slave
// Date:         Saturday, October 11, 2025
// Description:  A self-checking testbench for the adc_spi_slave module.
//
//               This testbench acts as an SPI master to verify all commands,
//               protocol edge cases, and functionality defined in the test plan.
//
//////////////////////////////////////////////////////////////////////////////////

`timescale 1ns / 1ps

module tb_adc_spi_slave;

    //--------------------------------------------------------------------------
    // Testbench Parameters
    //--------------------------------------------------------------------------
    localparam CLK_PERIOD = 10; // 100MHz system clock
    localparam SCK_PERIOD = CLK_PERIOD * 10; // SCK is 10x slower than CLK

    // DUT Parameters (mirrored for testbench convenience)
    localparam S_IDLE  = 2'b00;
    localparam READ    = 2'b00;
    localparam WRITE   = 2'b01;
    localparam SET     = 2'b10;
    localparam CLEAR   = 2'b11;

    localparam ADDR_CTRL_REG   = 2'b00;
    localparam ADDR_STATUS_REG = 2'b01;
    localparam ADDR_DATA_REG   = 2'b10;
    localparam ADDR_OFFSET_REG = 2'b11;

    //--------------------------------------------------------------------------
    // Testbench Signals
    //--------------------------------------------------------------------------
    reg         clk;
    reg         reset_;
    reg         sck;
    reg         cs;
    reg         mosi;
    wire        miso;

    integer     errors = 0;
    integer     test_case_count = 10;

    // Test sequencer variables
    reg [15:0] tx_word;
    reg [15:0] rx_word;
    reg [11:0] expected_val;

    //--------------------------------------------------------------------------
    // Instantiate the DUT
    //--------------------------------------------------------------------------
    adc_spi_slave dut (
        .clk(clk),
        .reset_(reset_),
        .sck(sck),
        .cs(cs),
        .mosi(mosi),
        .miso(miso)
    );

    //--------------------------------------------------------------------------
    // Clock and Reset Generation
    //--------------------------------------------------------------------------
    initial begin
        clk = 1'b0;
        forever #(CLK_PERIOD / 2) clk = ~clk;
    end

    initial begin
        sck = 1'b0;
        cs = 1'b1;
        mosi = 1'b0;
        reset_ = 1'b0;
        #(CLK_PERIOD * 5);
        reset_ = 1'b1;
    end

    //--------------------------------------------------------------------------
    // SPI Master Task (Protocol-Pure, Delay-Based)
    //--------------------------------------------------------------------------
    task spi_transaction(input [15:0] tx_data, output [15:0] rx_data);
        integer i;
    begin
        $display("@%0tns:   [SPI TX] -> 0x%h (CMD: %b, ADDR: %b, DATA: 0x%h)", $time, tx_data, tx_data[15:14], tx_data[13:12], tx_data[11:0]);
        cs = 1'b0;
        sck = 1'b0;
        #(SCK_PERIOD / 2);

        for (i = 15; i >= 0; i = i - 1) begin
            // 1. Master sets MOSI data while SCK is low
            mosi = tx_data[i];
            #(SCK_PERIOD / 2);

            // 2. Master raises SCK; Slave captures MOSI on this rising edge
            sck = 1'b1;
            #(SCK_PERIOD / 2);

            // 3. Master lowers SCK; Slave drives MISO on this falling edge
            sck = 1'b0;
            // 4. Master samples MISO now that it's stable
            rx_data[i] = miso;
        end
        
        cs = 1'b1;
        mosi = 1'b0; // Leave MOSI in a known idle state
        $display("@%0tns:   [SPI RX] <- 0x%h (DATA: 0x%h)", $time, rx_data, rx_data[11:0]);
        #(CLK_PERIOD * 2);
    end
    endtask


    //--------------------------------------------------------------------------
    // Test Sequencer
    //--------------------------------------------------------------------------
    initial begin
        $dumpfile("iverilog/wave_files/tb_adc_spi_slave.vcd");
        $dumpvars(0, tb_adc_spi_slave);
        
        $display("\n@%0tns: [INFO] Starting ADC SPI Slave Verification...\n", $time);

        @(posedge reset_);
        #(CLK_PERIOD);

        // --- Test Case 1: Reset Verification ---
        $display("@%0tns: --- Test Case 1: Reset Verification ---", $time);
        $display("  Action: Reading from ADDR_STATUS_REG to verify reset value.");
        tx_word = {READ, ADDR_STATUS_REG, 12'h000};
        spi_transaction(tx_word, rx_word);
        if (rx_word[11:0] === 12'h800) begin
            $display("@%0tns: [PASS] Device correctly reset and status_reg reads 0x800.", $time);
        end else begin
            $display("@%0tns: [FAIL] Device did not reset correctly. Read 0x%h from status_reg.", $time, rx_word[11:0]);
            errors = errors + 1;
        end

        // --- Test Case 2: Basic WRITE Command ---
        $display("\n@%0tns: --- Test Case 2: Basic WRITE Command ---", $time);
        $display("  Action: Writing 0xA5A to ADDR_CTRL_REG.");
        tx_word = {WRITE, ADDR_CTRL_REG, 12'hA5A};
        spi_transaction(tx_word, rx_word);
        $display("  Action: Reading back from ADDR_CTRL_REG to verify.");
        tx_word = {READ, ADDR_CTRL_REG, 12'h000};
        spi_transaction(tx_word, rx_word);
        if (rx_word[11:0] === 12'hA5A) begin
            $display("@%0tns: [PASS] WRITE command successfully updated ctrl_reg.", $time);
        end else begin
            $display("@%0tns: [FAIL] WRITE command failed. Expected 0x%h, Got 0x%h", $time, 12'hA5A, rx_word[11:0]);
            errors = errors + 1;
        end

        // --- Test Case 3: Basic READ Command ---
        $display("\n@%0tns: --- Test Case 3: Basic READ Command (from status_reg) ---", $time);
        $display("  Action: Reading from ADDR_STATUS_REG.");
        tx_word = {READ, ADDR_STATUS_REG, 12'h0};
        spi_transaction(tx_word, rx_word);
        if (rx_word[11:0] === 12'h800) begin
            $display("@%0tns: [PASS] READ command successfully returned status_reg value: 0x%h", $time, rx_word[11:0]);
        end else begin
            $display("@%0tns: [FAIL] READ command failed. Expected 0x%h, Got 0x%h", $time, 12'h800, rx_word[11:0]);
            errors = errors + 1;
        end

        // --- Test Case 4: SET Command ---
        $display("\n@%0tns: --- Test Case 4: SET Command ---", $time);
        $display("  Action: Writing initial value to ADDR_CTRL_REG.");
        spi_transaction({WRITE, ADDR_CTRL_REG, 12'b1100_0011_0011}, rx_word);
        $display("  Action: Sending SET command with bitmask.");
        spi_transaction({SET, ADDR_CTRL_REG, 12'b0000_1111_0000}, rx_word);
        expected_val = 12'b1100_1111_0011;
        $display("  Action: Reading back to verify SET operation.");
        spi_transaction({READ, ADDR_CTRL_REG, 12'h000}, rx_word);
        if (rx_word[11:0] === expected_val) begin
            $display("@%0tns: [PASS] SET command correctly performed bitwise OR.", $time);
        end else begin
            $display("@%0tns: [FAIL] SET command failed. Expected 0x%h, Got 0x%h", $time, expected_val, rx_word[11:0]);
            errors = errors + 1;
        end

        // --- Test Case 5: CLEAR Command ---
        $display("\n@%0tns: --- Test Case 5: CLEAR Command ---", $time);
        $display("  Action: Writing initial value to ADDR_CTRL_REG.");
        spi_transaction({WRITE, ADDR_CTRL_REG, 12'b1100_1111_0011}, rx_word);
        $display("  Action: Sending CLEAR command with bitmask.");
        spi_transaction({CLEAR, ADDR_CTRL_REG, 12'b1100_0000_1100}, rx_word);
        expected_val = 12'b0000_1111_0011;
        $display("  Action: Reading back to verify CLEAR operation.");
        spi_transaction({READ, ADDR_CTRL_REG, 12'h000}, rx_word);
        if (rx_word[11:0] === expected_val) begin
            $display("@%0tns: [PASS] CLEAR command correctly performed bitwise AND-NOT.", $time);
        end else begin
            $display("@%0tns: [FAIL] CLEAR command failed. Expected 0x%h, Got 0x%h", $time, expected_val, rx_word[11:0]);
            errors = errors + 1;
        end

        // --- Test Case 6: Write to Read-Only Address ---
        $display("\n@%0tns: --- Test Case 6: Write to Read-Only Address ---", $time);
        expected_val = 12'h800;
        $display("  Action: Attempting to write 0xBAD to read-only ADDR_STATUS_REG.");
        spi_transaction({WRITE, ADDR_STATUS_REG, 12'hBAD}, rx_word);
        $display("  Action: Reading back to verify register was not changed.");
        spi_transaction({READ, ADDR_STATUS_REG, 12'h000}, rx_word);
        if (rx_word[11:0] === expected_val) begin
            $display("@%0tns: [PASS] Write to read-only address was correctly ignored.", $time);
        end else begin
            $display("@%0tns: [FAIL] Write to read-only address was not ignored. Got 0x%h", $time, rx_word[11:0]);
            errors = errors + 1;
        end

        // --- Test Case 7: Back-to-Back Transactions ---
        $display("\n@%0tns: --- Test Case 7: Back-to-Back Transactions ---", $time);
        $display("  Action: Asserting CS for two consecutive transactions.");
        cs = 1'b0;
        sck = 1'b0;
        #(SCK_PERIOD / 2);
        // Transaction 1: WRITE
        $display("  Action: Transaction 1 - WRITE 0xCDE to ADDR_CTRL_REG.");
        tx_word = {WRITE, ADDR_CTRL_REG, 12'hCDE};
        for (integer i = 15; i >= 0; i = i - 1) begin
             mosi = tx_word[i]; #(SCK_PERIOD/2); sck=1'b1; #(SCK_PERIOD/2); sck=1'b0;
        end
        #(CLK_PERIOD * 4); // Give DUT time to latch
        // Transaction 2: READ
        $display("  Action: Transaction 2 - READ from ADDR_CTRL_REG.");
        tx_word = {READ, ADDR_CTRL_REG, 12'h0};
        for (integer i = 15; i >= 0; i = i - 1) begin
             mosi = tx_word[i]; #(SCK_PERIOD/2); sck=1'b1; #(SCK_PERIOD/2); sck=1'b0; rx_word[i] = miso;
        end
        cs = 1'b1;
        $display("@%0tns:   [SPI RX] <- 0x%h (DATA: 0x%h)", $time, rx_word, rx_word[11:0]);
        #(CLK_PERIOD * 2);
        if (rx_word[11:0] === 12'hCDE) begin
            $display("@%0tns: [PASS] Back-to-back transactions handled correctly.", $time);
        end else begin
            $display("@%0tns: [FAIL] Back-to-back read failed. Expected 0x%h, Got 0x%h", $time, 12'hCDE, rx_word[11:0]);
            errors = errors + 1;
        end

        // --- Test Case 8: Transaction Abort by CS ---
        $display("\n@%0tns: --- Test Case 8: Transaction Abort by CS ---", $time);
        $display("  Action: Writing a known start value (0x123) to ADDR_CTRL_REG.");
        spi_transaction({WRITE, ADDR_CTRL_REG, 12'h123}, rx_word);
        expected_val = 12'h123;
        $display("  Action: Starting a new WRITE, but will abort by de-asserting CS early.");
        tx_word = {WRITE, ADDR_CTRL_REG, 12'hFFF};
        cs = 1'b0;
        sck = 1'b0;
        #(SCK_PERIOD / 2);
        for (integer i = 15; i >= 6; i = i - 1) begin // Only send 10 bits
            mosi = tx_word[i]; #(SCK_PERIOD/2); sck=1'b1; #(SCK_PERIOD/2); sck=1'b0;
        end
        cs = 1'b1;
        $display("@%0tns:   Action: CS de-asserted. Transaction aborted.", $time);
        #(CLK_PERIOD*2);
        $display("  Action: Reading back from ADDR_CTRL_REG to verify it was not corrupted.");
        spi_transaction({READ, ADDR_CTRL_REG, 12'h000}, rx_word);
        if (rx_word[11:0] === expected_val) begin
            $display("@%0tns: [PASS] Transaction abort did not corrupt ctrl_reg.", $time);
        end else begin
            $display("@%0tns: [FAIL] Transaction abort corrupted ctrl_reg. Expected 0x%h, Got 0x%h", $time, expected_val, rx_word[11:0]);
            errors = errors + 1;
        end

        // --- Test Case 9: Idle Clocking (CS High) ---
        $display("\n@%0tns: --- Test Case 9: Idle Clocking (CS High) ---", $time);
        cs = 1'b1;
        $display("  Action: Toggling SCK 20 times while CS is high.");
        for (integer i = 0; i < 20; i = i + 1) begin
             sck = ~sck; #(SCK_PERIOD / 2);
        end
        $display("  Action: Verifying state is still IDLE by performing a valid transaction.");
        spi_transaction({READ, ADDR_STATUS_REG, 12'h000}, rx_word);
        if (rx_word[11:0] == 12'h800) begin
            $display("@%0tns: [PASS] FSM remained in IDLE while unselected SCK toggled.", $time);
        end else begin
            $display("@%0tns: [FAIL] FSM left IDLE state while unselected.", $time);
            errors = errors + 1;
        end

        // --- Test Case 10: Read from all addresses ---
        $display("\n@%0tns: --- Test Case 10: Read from all addresses ---", $time);
        $display("  Action: Reading from ADDR_DATA_REG and ADDR_OFFSET_REG.");
        spi_transaction({READ, ADDR_DATA_REG, 12'h000}, rx_word);
        if(rx_word[11:0] != 12'h0) errors = errors + 1;
        spi_transaction({READ, ADDR_OFFSET_REG, 12'h000}, rx_word);
        if(rx_word[11:0] != 12'h0) errors = errors + 1;
        $display("@%0tns: [PASS] All remaining registers read successfully.", $time);


        // --- Final Summary ---
        if (errors == 0) begin
            $display("\n@%0tns: [INFO] All %0d test cases PASSED!", $time, test_case_count);
        end else begin
            $display("\n@%0tns: [INFO] %0d out of %0d test cases FAILED.", $time, errors, test_case_count);
        end
        $finish;
    end

endmodule

iverilog/wave_files/tb_adc_spi_slave.vcd
$date
	Sat Oct 11 15:16:13 2025
$end
$version
	Icarus Verilog
$end
$timescale
	1ps
$end
$scope module tb_adc_spi_slave $end
$var wire 1 ! miso $end
$var parameter 2 " ADDR_CTRL_REG $end
$var parameter 2 # ADDR_DATA_REG $end
$var parameter 2 $ ADDR_OFFSET_REG $end
$var parameter 2 % ADDR_STATUS_REG $end
$var parameter 2 & CLEAR $end
$var parameter 32 ' CLK_PERIOD $end
$var parameter 2 ( READ $end
$var parameter 64 ) SCK_PERIOD $end
$var parameter 2 * SET $end
$var parameter 2 + S_IDLE $end
$var parameter 2 , WRITE $end
$var reg 1 - clk $end
$var reg 1 . cs $end
$var reg 12 / expected_val [11:0] $end
$var reg 1 0 mosi $end
$var reg 1 1 reset_ $end
$var reg 16 2 rx_word [15:0] $end
$var reg 1 3 sck $end
$var reg 16 4 tx_word [15:0] $end
$var integer 32 5 errors [31:0] $end
$var integer 32 6 test_case_count [31:0] $end
$scope module dut $end
$var wire 1 - clk $end
$var wire 1 . cs $end
$var wire 1 0 mosi $end
$var wire 1 7 negedge_sck_pulse $end
$var wire 1 8 posedge_sck_pulse $end
$var wire 1 1 reset_ $end
$var wire 1 3 sck $end
$var wire 12 9 mosi_data_buffer [11:0] $end
$var wire 1 ! miso $end
$var wire 2 : cmd_buffer [1:0] $end
$var wire 2 ; addr_buffer [1:0] $end
$var parameter 2 < ADDR_CTRL_REG $end
$var parameter 2 = ADDR_DATA_REG $end
$var parameter 2 > ADDR_OFFSET_REG $end
$var parameter 2 ? ADDR_STATUS_REG $end
$var parameter 2 @ CLEAR $end
$var parameter 2 A READ $end
$var parameter 2 B SET $end
$var parameter 2 C S_IDLE $end
$var parameter 2 D S_LATCH $end
$var parameter 2 E S_SHIFT $end
$var parameter 2 F WRITE $end
$var reg 5 G counter [4:0] $end
$var reg 12 H ctrl_reg [11:0] $end
$var reg 12 I data_reg [11:0] $end
$var reg 12 J miso_data_buffer [11:0] $end
$var reg 2 K next_state [1:0] $end
$var reg 12 L offset_reg [11:0] $end
$var reg 1 M sck_sync1 $end
$var reg 1 N sck_sync2 $end
$var reg 16 O shift_reg [15:0] $end
$var reg 2 P state_reg [1:0] $end
$var reg 12 Q status_reg [11:0] $end
$upscope $end
$scope begin $ivl_for_loop0 $end
$var integer 32 R i [31:0] $end
$upscope $end
$scope begin $ivl_for_loop1 $end
$var integer 32 S i [31:0] $end
$upscope $end
$scope begin $ivl_for_loop2 $end
$var integer 32 T i [31:0] $end
$upscope $end
$scope begin $ivl_for_loop3 $end
$var integer 32 U i [31:0] $end
$upscope $end
$scope task spi_transaction $end
$var reg 16 V rx_data [15:0] $end
$var reg 16 W tx_data [15:0] $end
$var integer 32 X i [31:0] $end
$upscope $end
$upscope $end
$enddefinitions $end
$comment Show the parameter values. $end
$dumpall
b1 F
b1 E
b11 D
b0 C
b10 B
b0 A
b11 @
b1 ?
b11 >
b10 =
b0 <
b1 ,
b0 +
b10 *
b1100100 )
b0 (
b1010 '
b11 &
b1 %
b11 $
b10 #
b0 "
$end
#0
$dumpvars
bx X
bx W
bx V
bx U
bx T
bx S
bx R
b100000000000 Q
b0 P
b0 O
0N
0M
b0 L
b0 K
b0 J
b0 I
b0 H
b0 G
b0 ;
b0 :
b0 9
08
07
b1010 6
b0 5
bx 4
03
bx 2
01
00
bx /
1.
0-
z!
$end
#5000
1-
#10000
0-
#15000
1-
#20000
0-
#25000
1-
#30000
0-
#35000
1-
#40000
0-
#45000
1-
#50000
0-
11
#55000
1-
#60000
b1 K
0!
0-
0.
b1000000000000 W
b1000000000000 4
#65000
b1 P
1-
#70000
0-
#75000
1-
#80000
0-
#85000
1-
#90000
0-
#95000
1-
#100000
0-
#105000
1-
#110000
0-
b1111 X
#115000
1-
#120000
0-
#125000
1-
#130000
0-
#135000
1-
#140000
0-
#145000
1-
#150000
0-
#155000
1-
#160000
0-
13
#165000
18
1M
1-
#170000
0-
#175000
08
1N
b1 G
1-
#180000
0-
#185000
1-
#190000
0-
#195000
1-
#200000
0-
#205000
1-
#210000
0-
b1110 X
b0xxxxxxxxxxxxxxx V
03
#215000
17
0M
1-
#220000
0-
#225000
07
0N
1-
#230000
0-
#235000
1-
#240000
0-
#245000
1-
#250000
0-
#255000
1-
#260000
0-
13
#265000
18
1M
1-
#270000
0-
#275000
08
1N
b10 G
1-
#280000
0-
#285000
1-
#290000
0-
#295000
1-
#300000
0-
#305000
1-
#310000
0-
b1101 X
b0xxxxxxxxxxxxxx V
03
#315000
17
0M
1-
#320000
0-
#325000
07
0N
1-
#330000
0-
#335000
1-
#340000
0-
#345000
1-
#350000
0-
#355000
1-
#360000
0-
13
#365000
18
1M
1-
#370000
0-
#375000
08
1N
b11 G
1-
#380000
0-
#385000
1-
#390000
0-
#395000
1-
#400000
0-
#405000
1-
#410000
0-
10
b1100 X
b0xxxxxxxxxxxxx V
03
#415000
17
0M
1-
#420000
0-
#425000
07
0N
1-
#430000
0-
#435000
1-
#440000
0-
#445000
1-
#450000
0-
#455000
1-
#460000
0-
13
#465000
18
1M
1-
#470000
0-
#475000
08
b1 ;
1N
b100 G
b1000000000000 O
1-
#480000
0-
#485000
1!
b100000000000 J
1-
#490000
0-
#495000
1-
#500000
0-
#505000
1-
#510000
0-
00
b1011 X
b1xxxxxxxxxxxx V
03
#515000
17
0M
1-
#520000
0-
#525000
07
0N
1-
#530000
0-
#535000
1-
#540000
0-
#545000
1-
#550000
0-
#555000
1-
#560000
0-
13
#565000
18
1M
1-
#570000
0-
#575000
08
1N
b101 G
1-
#580000
0-
#585000
1-
#590000
0-
#595000
1-
#600000
0-
#605000
1-
#610000
0-
b1010 X
b11xxxxxxxxxxx V
03
#615000
17
0M
1-
#620000
0-
#625000
0!
07
b0 J
0N
1-
#630000
0-
#635000
1-
#640000
0-
#645000
1-
#650000
0-
#655000
1-
#660000
0-
13
#665000
18
1M
1-
#670000
0-
#675000
08
1N
b110 G
1-
#680000
0-
#685000
1-
#690000
0-
#695000
1-
#700000
0-
#705000
1-
#710000
0-
b1001 X
b110xxxxxxxxxx V
03
#715000
17
0M
1-
#720000
0-
#725000
07
0N
1-
#730000
0-
#735000
1-
#740000
0-
#745000
1-
#750000
0-
#755000
1-
#760000
0-
13
#765000
18
1M
1-
#770000
0-
#775000
08
1N
b111 G
1-
#780000
0-
#785000
1-
#790000
0-
#795000
1-
#800000
0-
#805000
1-
#810000
0-
b1000 X
b1100xxxxxxxxx V
03
#815000
17
0M
1-
#820000
0-
#825000
07
0N
1-
#830000
0-
#835000
1-
#840000
0-
#845000
1-
#850000
0-
#855000
1-
#860000
0-
13
#865000
18
1M
1-
#870000
0-
#875000
08
1N
b1000 G
1-
#880000
0-
#885000
1-
#890000
0-
#895000
1-
#900000
0-
#905000
1-
#910000
0-
b111 X
b11000xxxxxxxx V
03
#915000
17
0M
1-
#920000
0-
#925000
07
0N
1-
#930000
0-
#935000
1-
#940000
0-
#945000
1-
#950000
0-
#955000
1-
#960000
0-
13
#965000
18
1M
1-
#970000
0-
#975000
08
1N
b1001 G
1-
#980000
0-
#985000
1-
#990000
0-
#995000
1-
#1000000
0-
#1005000
1-
#1010000
0-
b110 X
b110000xxxxxxx V
03
#1015000
17
0M
1-
#1020000
0-
#1025000
07
0N
1-
#1030000
0-
#1035000
1-
#1040000
0-
#1045000
1-
#1050000
0-
#1055000
1-
#1060000
0-
13
#1065000
18
1M
1-
#1070000
0-
#1075000
08
1N
b1010 G
1-
#1080000
0-
#1085000
1-
#1090000
0-
#1095000
1-
#1100000
0-
#1105000
1-
#1110000
0-
b101 X
b1100000xxxxxx V
03
#1115000
17
0M
1-
#1120000
0-
#1125000
07
0N
1-
#1130000
0-
#1135000
1-
#1140000
0-
#1145000
1-
#1150000
0-
#1155000
1-
#1160000
0-
13
#1165000
18
1M
1-
#1170000
0-
#1175000
08
1N
b1011 G
1-
#1180000
0-
#1185000
1-
#1190000
0-
#1195000
1-
#1200000
0-
#1205000
1-
#1210000
0-
b100 X
b11000000xxxxx V
03
#1215000
17
0M
1-
#1220000
0-
#1225000
07
0N
1-
#1230000
0-
#1235000
1-
#1240000
0-
#1245000
1-
#1250000
0-
#1255000
1-
#1260000
0-
13
#1265000
18
1M
1-
#1270000
0-
#1275000
08
1N
b1100 G
1-
#1280000
0-
#1285000
1-
#1290000
0-
#1295000
1-
#1300000
0-
#1305000
1-
#1310000
0-
b11 X
b110000000xxxx V
03
#1315000
17
0M
1-
#1320000
0-
#1325000
07
0N
1-
#1330000
0-
#1335000
1-
#1340000
0-
#1345000
1-
#1350000
0-
#1355000
1-
#1360000
0-
13
#1365000
18
1M
1-
#1370000
0-
#1375000
08
1N
b1101 G
1-
#1380000
0-
#1385000
1-
#1390000
0-
#1395000
1-
#1400000
0-
#1405000
1-
#1410000
0-
b10 X
b1100000000xxx V
03
#1415000
17
0M
1-
#1420000
0-
#1425000
07
0N
1-
#1430000
0-
#1435000
1-
#1440000
0-
#1445000
1-
#1450000
0-
#1455000
1-
#1460000
0-
13
#1465000
18
1M
1-
#1470000
0-
#1475000
08
1N
b1110 G
1-
#1480000
0-
#1485000
1-
#1490000
0-
#1495000
1-
#1500000
0-
#1505000
1-
#1510000
0-
b1 X
b11000000000xx V
03
#1515000
17
0M
1-
#1520000
0-
#1525000
07
0N
1-
#1530000
0-
#1535000
1-
#1540000
0-
#1545000
1-
#1550000
0-
#1555000
1-
#1560000
0-
13
#1565000
18
1M
1-
#1570000
0-
#1575000
08
1N
b1111 G
1-
#1580000
0-
#1585000
1-
#1590000
0-
#1595000
1-
#1600000
0-
#1605000
1-
#1610000
0-
b0 X
b110000000000x V
03
#1615000
17
0M
1-
#1620000
0-
#1625000
07
0N
1-
#1630000
0-
#1635000
1-
#1640000
0-
#1645000
1-
#1650000
0-
#1655000
1-
#1660000
0-
13
#1665000
18
1M
1-
#1670000
0-
#1675000
08
b11 K
1N
b10000 G
1-
#1680000
0-
#1685000
b1 K
b11 P
1-
#1690000
0-
#1695000
b1 P
b0 G
1-
#1700000
0-
#1705000
1-
#1710000
b11 K
z!
0-
1.
b11111111111111111111111111111111 X
b1100000000000 V
03
#1715000
17
b0 K
0M
b11 P
1-
#1720000
0-
#1725000
07
b0 P
0N
1-
#1730000
b1 K
0!
0-
0.
b100101001011010 W
b100101001011010 4
b1100000000000 2
#1735000
b1 P
1-
#1740000
0-
#1745000
1-
#1750000
0-
#1755000
1-
#1760000
0-
#1765000
1-
#1770000
0-
#1775000
1-
#1780000
0-
b1111 X
#1785000
1-
#1790000
0-
#1795000
1-
#1800000
0-
#1805000
1-
#1810000
0-
#1815000
1-
#1820000
0-
#1825000
1-
#1830000
0-
13
#1835000
18
1M
1-
#1840000
0-
#1845000
08
b1 G
1N
1-
#1850000
0-
#1855000
1-
#1860000
0-
#1865000
1-
#1870000
0-
#1875000
1-
#1880000
0-
10
b1110 X
03
#1885000
17
0M
1-
#1890000
0-
#1895000
07
0N
1-
#1900000
0-
#1905000
1-
#1910000
0-
#1915000
1-
#1920000
0-
#1925000
1-
#1930000
0-
13
#1935000
18
1M
1-
#1940000
0-
#1945000
08
b1 :
b10 G
b101000000000000 O
1N
1-
#1950000
0-
#1955000
1-
#1960000
0-
#1965000
1-
#1970000
0-
#1975000
1-
#1980000
0-
00
b1101 X
03
#1985000
17
0M
1-
#1990000
0-
#1995000
07
0N
1-
#2000000
0-
#2005000
1-
#2010000
0-
#2015000
1-
#2020000
0-
#2025000
1-
#2030000
0-
13
#2035000
18
1M
1-
#2040000
0-
#2045000
08
b11 G
1N
1-
#2050000
0-
#2055000
1-
#2060000
0-
#2065000
1-
#2070000
0-
#2075000
1-
#2080000
0-
b1100 X
03
#2085000
17
0M
1-
#2090000
0-
#2095000
07
0N
1-
#2100000
0-
#2105000
1-
#2110000
0-
#2115000
1-
#2120000
0-
#2125000
1-
#2130000
0-
13
#2135000
18
1M
1-
#2140000
0-
#2145000
08
b0 ;
b100 G
b100000000000000 O
1N
1-
#2150000
0-
#2155000
1-
#2160000
0-
#2165000
1-
#2170000
0-
#2175000
1-
#2180000
0-
10
b1011 X
b100000000000 V
03
#2185000
17
0M
1-
#2190000
0-
#2195000
07
0N
1-
#2200000
0-
#2205000
1-
#2210000
0-
#2215000
1-
#2220000
0-
#2225000
1-
#2230000
0-
13
#2235000
18
1M
1-
#2240000
0-
#2245000
08
b100000000000 9
b101 G
b100100000000000 O
1N
1-
#2250000
0-
#2255000
1-
#2260000
0-
#2265000
1-
#2270000
0-
#2275000
1-
