adc_controller.v
/*
 * =================================================================================
 * Module:      adc_controller
 *
 * Description: A Finite State Machine (FSM) based controller for a
 * Successive Approximation (SAR) ADC. This version uses an
 * integrated, standard SAR logic implementation for optimal performance.
 *
 * Features:
 * - Parameterized data width ('WIDTH') for different ADC resolutions.
 * - Standard single conversion handshaking protocol.
 * - Continuous conversion mode (if 'en_' is held low).
 * - Dedicated 'dac_en' signal to enable the external DAC.
 * - FSM is implemented using the robust "three-process" style.
 * - Datapath logic uses a high-performance distributed model.
 * =================================================================================
 */
module adc_controller #(
    parameter WIDTH = 12 // Default ADC resolution
)(
    // Control and Clock Inputs
    input        clk,        // System clock
    input        reset_,     // Asynchronous, active-low reset
    input        en_,        // Active-low enable to start a conversion

    // ADC Interface
    input        comparator, // Input from the external voltage comparator

    // Outputs
    output       sample_and_hold, // Control signal for the S&H circuit
    output       dac_en,     // Enable signal for the external DAC
    output       ack,        // Acknowledgment: high when conversion is done
    output [WIDTH-1:0] dac,        // Output value to drive the external DAC
    output [WIDTH-1:0] data        // Final, valid conversion result
);

    // -- State Parameters --
    localparam S_IDLE    = 2'b00;
    localparam S_INIT    = 2'b01;
    localparam S_CONVERT = 2'b10;
    localparam S_FINISH  = 2'b11;

    // -- Internal Signals --
    reg  [1:0]   state, next_state;

    // Data path registers
    reg  [WIDTH-1:0]  dac_reg;      // Holds the current confirmed result
    reg  [WIDTH-1:0]  counter_reg;  // Holds the bit-mask for the current test
    reg  [WIDTH-1:0]  data_out_reg; // Dedicated stable output register

    // -- Wires for internal logic --
    // 'test_value' is the value sent to the DAC for comparison in the CONVERT state.
    wire [WIDTH-1:0]  test_value;
    // 'is_final_bit' is a status flag, high during the last conversion cycle (LSB).
    wire              is_final_bit;

    // ============================================================================
    // FSM LOGIC (Three-Process Implementation)
    // ============================================================================

    // -- FSM Process 1: State Register (Sequential) --
    always @(posedge clk, negedge reset_) begin
        if (!reset_)
            state <= S_IDLE;
        else
            state <= next_state;
    end

    // -- FSM Process 2: Next-State Logic (Combinational) --
    always @* begin
        next_state = state;
        case (state)
            S_IDLE: begin
                if (!en_) next_state = S_INIT;
            end
            S_INIT: begin
                next_state = S_CONVERT;
            end
            S_CONVERT: begin
                if (en_) begin
                    // If en_ goes high mid-conversion, abort and go to IDLE.
                    next_state = S_IDLE;
                end else if (is_final_bit) begin
                    next_state = S_FINISH;
                end
            end
            S_FINISH: begin
                if (en_) next_state = S_IDLE;   // Single mode complete
                else     next_state = S_INIT;   // Continuous mode restart
            end
            default: begin
                next_state = S_IDLE;
            end
        endcase
    end

    // -- FSM Process 3: Output Logic (Combinational) --
    assign sample_and_hold = (state == S_INIT);
    assign ack             = (state == S_FINISH);
    assign dac_en          = (state == S_INIT) || (state == S_CONVERT);


    // ============================================================================
    // DATA PATH LOGIC
    // ============================================================================

    // -- Combinational Datapath Logic --
    // The "test value" is the current result with the next bit-to-test set to 1.
    assign test_value   = dac_reg | counter_reg;
    // The final bit is being processed when the counter mask is 1 (the LSB).
    assign is_final_bit = (counter_reg == 1);

    // -- Sequential Datapath Logic --
    always @(posedge clk, negedge reset_) begin
        if (!reset_) begin
            dac_reg      <= {WIDTH{1'b0}};
            counter_reg  <= {WIDTH{1'b0}};
            data_out_reg <= {WIDTH{1'b0}};
        end else begin
            case (state)
                S_INIT: begin
                    // For the standard algorithm, the result register must start at 0.
                    dac_reg     <= {WIDTH{1'b0}};
                    // The counter starts with only the MSB set.
                    counter_reg <= (1'b1 << (WIDTH - 1));
                end
                S_CONVERT: begin
                    // This is the core SAR logic, implemented as a multiplexer.
                    // If comparator is high, we keep the bit by updating dac_reg.
                    if (comparator) begin
                        dac_reg <= test_value;
                    end
                    // If comparator is low, we discard the bit by doing nothing
                    // to dac_reg, so it holds its previous value.

                    // Always shift the counter to test the next bit.
                    counter_reg <= counter_reg >> 1;

                    // On the final conversion cycle, latch the final correct result
                    // into the stable data output register.
                    if (is_final_bit) begin
                        // This ternary operator describes the final mux selection for the LSB.
                        data_out_reg <= comparator ? test_value : dac_reg;
                    end
                end
                default: begin
                    // For S_IDLE and S_FINISH, explicitly hold all register values.
                    // This is good practice for linters and design clarity.
                    dac_reg      <= dac_reg;
                    counter_reg  <= counter_reg;
                    data_out_reg <= data_out_reg;
                end
            endcase
        end
    end

    // -- Final Output Assignments --
    // In the CONVERT state, the DAC is driven by the 'test_value'. In all other
    // states, it is driven by the stable, confirmed 'dac_reg' value.
    assign dac  = (state == S_CONVERT) ? test_value : dac_reg;
    // The final data output is always driven by the stable output register.
    assign data = data_out_reg;

endmodule

iverilog/testbench/tb_adc_controller.v
`timescale 1ns / 1ps

module tb_adc_controller;

    // -- Testbench Parameters --
    localparam WIDTH = 12;

    // -- Testbench Signals --
    reg                           clk;
    reg                           reset_;
    reg                           en_;
    reg  [WIDTH-1:0]              analog_input_equivalent;

    wire                          sample_and_hold;
    wire                          dac_en;
    wire                          ack;
    wire [WIDTH-1:0]              dac;
    wire [WIDTH-1:0]              data;
    wire                          comparator;

    // -- Local variable declarations for test scenarios --
    reg [WIDTH-1:0]                 first_result;
    localparam OVERSAMPLE_BITS    = 2;
    localparam NUM_SAMPLES        = 16;
    localparam AVG_SHIFT          = $clog2(NUM_SAMPLES);
    // Moved HALF_DIVISOR to module scope for Verilog-2005 compatibility
    localparam HALF_DIVISOR       = (1 << (AVG_SHIFT - 1));
    reg [WIDTH+OVERSAMPLE_BITS-1:0] true_oversampled_value;
    reg [WIDTH-1:0]                 noisy_sample;
    reg signed [2:0]                noise;
    reg [WIDTH+AVG_SHIFT-1:0]       accumulator;
    reg [WIDTH+OVERSAMPLE_BITS-1:0] oversampled_result;
    reg [WIDTH-1:0]                 averaged_result_trunc; // Truncated average
    reg [WIDTH-1:0]                 averaged_result_round; // Rounded average
    integer                         seed;

    // ============================================================================
    // Custom Pseudo-Random Number Generator (PRNG)
    // ============================================================================
    task automatic get_random(output [31:0] result, input integer min, max);
        begin
            seed = (seed * 1664525 + 1013904223);
            result = min + (seed % (max - min + 1));
        end
    endtask

    // -- Instantiate the Device Under Test (DUT) --
    adc_controller #(
        .WIDTH(WIDTH)
    ) u_dut (
        .clk(clk),
        .reset_(reset_),
        .en_(en_),
        .comparator(comparator),
        .sample_and_hold(sample_and_hold),
        .dac_en(dac_en),
        .ack(ack),
        .dac(dac),
        .data(data)
    );

    // -- Comparator Modeling --
    assign comparator = (analog_input_equivalent >= dac);

    // -- Clock Generation --
    always #5 clk = ~clk;

    // -- Main Test Sequence --
    initial begin
        if (!$value$plusargs("SEED=%d", seed)) begin
            seed = 1; // Default seed if none is provided
        end
        $display("Simulation running with seed: %d", seed);
        
        $dumpfile("iverilog/wave_files/tb_adc_controller.vcd");
        $dumpvars(0, tb_adc_controller);

        // Initial state and Reset
        $display("--------------------------------------------------");
        $display("Simulation Start: Applying Reset");
        $display("--------------------------------------------------");
        clk <= 0; reset_ <= 0; en_ <= 1;
        #20;
        reset_ <= 1;
        #10;

        // SCENARIO 1: SINGLE CONVERSIONS
        $display("\n--- SCENARIO 1: SINGLE CONVERSIONS (WIDTH=%0d) ---", WIDTH);
        for (integer i = 0; i < 2; i = i + 1) begin
            get_random(analog_input_equivalent, 0, (1<<WIDTH)-1);
            $display("\nTest 1.%0d: Starting single conversion for value %4d (0x%h)", i, analog_input_equivalent, analog_input_equivalent);
            en_ <= 0;
            @(posedge clk);
            $display("Waiting for ACK...");
            @(posedge ack);
            $display("ACK received! Conversion complete.");
            en_ <= 1;
            $display("Expected: %4d (0x%h), Received: %4d (0x%h)", analog_input_equivalent, analog_input_equivalent, data, data);
            if (data == analog_input_equivalent) $display("Result: PASS"); else $display("Result: FAIL");
            #50;
        end

        // SCENARIO 2: CONTINUOUS CONVERSION
        $display("\n--- SCENARIO 2: CONTINUOUS CONVERSION ---");
        en_ <= 0;
        
        get_random(analog_input_equivalent, 0, (1<<WIDTH)-1);
        $display("\nTest 2.0: Continuous conversion 1 for value %4d (0x%h)", analog_input_equivalent, analog_input_equivalent);
        @(posedge ack);
        $display("ACK 1 received.");
        if (data == analog_input_equivalent) $display("Result 1: PASS"); else $display("Result 1: FAIL");
        first_result = data;
        
        get_random(analog_input_equivalent, 0, (1<<WIDTH)-1);
        $display("\nTest 2.1: Continuous conversion 2 for value %4d (0x%h)", analog_input_equivalent, analog_input_equivalent);
        $display("Verifying previous data is stable...");
        if (data == first_result) $display("Previous data is STABLE. PASS."); else $display("Previous data CHANGED. FAIL.");
        @(posedge ack);
        $display("ACK 2 received.");
        if (data == analog_input_equivalent) $display("Result 2: PASS"); else $display("Result 2: FAIL");
        
        en_ <= 1;
        #50;

        // SCENARIO 3: OVERSAMPLING & AVERAGING
        $display("\n--- SCENARIO 3: OVERSAMPLING & AVERAGING ---");

        get_random(true_oversampled_value, 0, (1<<(WIDTH+OVERSAMPLE_BITS))-1);
        $display("Goal: Measure %0d-bit value %d (0x%h) by oversampling.", WIDTH+OVERSAMPLE_BITS, true_oversampled_value, true_oversampled_value);
        
        accumulator = 0;
        en_ <= 0;
        
        for (integer i = 0; i < NUM_SAMPLES; i = i + 1) begin
            get_random(noise, 0, 4);
            noise = noise - 2;
            noisy_sample = (true_oversampled_value >> OVERSAMPLE_BITS) + noise;
            analog_input_equivalent = noisy_sample;
            @(posedge ack);
            accumulator = accumulator + data;
        end
        
        en_ <= 1;
        
        // --- Decimation Logic with Truncation and Rounding ---
        oversampled_result = accumulator >> OVERSAMPLE_BITS;
        averaged_result_trunc = accumulator >> AVG_SHIFT;
        averaged_result_round = (accumulator + HALF_DIVISOR) >> AVG_SHIFT;

        $display("\nOversampling Result (%0d-bit):", WIDTH+OVERSAMPLE_BITS);
        $display("True Value : %d (0x%h)", true_oversampled_value, true_oversampled_value);
        $display("Result     : %d (0x%h)", oversampled_result, oversampled_result);
        
        $display("\nAveraging Result (%0d-bit):", WIDTH);
        $display("True Value (%0d MSBs) : %d (0x%h)", WIDTH, true_oversampled_value >> OVERSAMPLE_BITS, true_oversampled_value >> OVERSAMPLE_BITS);
        $display("Truncated Result      : %d (0x%h)", averaged_result_trunc, averaged_result_trunc);
        $display("Rounded Result        : %d (0x%h)", averaged_result_round, averaged_result_round);
        #50;


        // ==================================================
        // Test Scenario 4: Mid-Conversion Reset Test (Corrected)
        // ==================================================
        $display("\n--- SCENARIO 4: MID-CONVERSION RESET TEST ---");
        get_random(analog_input_equivalent, 0, (1<<WIDTH)-1);
        $display("\nTest 4.0: Starting conversion for value %d...", analog_input_equivalent);
        
        // ** FIX: Hold en_ low to keep the conversion active **
        en_ <= 0;
        @(posedge clk);

        // Let the conversion run for a few cycles to ensure it's in S_CONVERT
        $display("Letting conversion run for 5 cycles...");
        repeat (5) @(posedge clk);

        $display("Asserting reset_ during conversion...");
        reset_ <= 0; // Assert reset
        #2; // Wait a moment to check async behavior
        if (u_dut.state == 2'b00) $display("STATE CHECK: FSM correctly returned to IDLE. PASS.");
        else $display("STATE CHECK: FSM did NOT return to IDLE. FAIL.");
        
        #20;
        reset_ <= 1; // De-assert reset
        @(posedge clk);

        $display("\nTest 4.1: Verifying controller can run a new conversion after reset.");
        get_random(analog_input_equivalent, 0, (1<<WIDTH)-1);
        $display("Starting new conversion for value %d...", analog_input_equivalent);
        en_ <= 0;
        @(posedge clk);
        $display("Waiting for ACK...");
        @(posedge ack);
        $display("ACK received! Conversion complete.");
        en_ <= 1;
        if (data == analog_input_equivalent) $display("Result: PASS"); else $display("Result: FAIL");
        #50;

        


        // ==================================================
        // Test Scenario 5: Mid-Conversion Enable/Abort Test
        // ==================================================
        $display("\n--- SCENARIO 5: MID-CONVERSION ABORT TEST ---");
        get_random(analog_input_equivalent, 0, (1<<WIDTH)-1);
        $display("\nTest 5.0: Starting conversion for value %d...", analog_input_equivalent);
        en_ <= 0; // Assert enable to start conversion
        @(posedge clk); // Allow FSM to leave IDLE

        // Let the conversion run for a few cycles to ensure it's in S_CONVERT
        $display("Letting conversion run for 5 cycles...");
        repeat (5) @(posedge clk);

        $display("De-asserting en_ during conversion to signal abort...");
        en_ <= 1; // Signal the abort
        
        // Wait for the NEXT clock edge to ensure the state has settled.
        @(posedge clk); 
        #1
        
        // Check if the FSM correctly returned to the IDLE state.
        if (u_dut.state == 2'b00) begin
            $display("STATE CHECK: FSM correctly aborted and returned to IDLE. PASS.");
        end else begin
            $display("STATE CHECK: FSM did NOT return to IDLE. FAIL. (State is %b)", u_dut.state);
        end
        #50; // Delay for waveform clarity



        $display("\n--------------------------------------------------");
        $display("All tests complete. Ending simulation.");
        $display("--------------------------------------------------");
        $finish;
    end

endmodule

iverilog/wave_files/tb_adc_controller.vcd
$date
	Sat Oct 11 14:07:42 2025
$end
$version
	Icarus Verilog
$end
$timescale
	1ps
$end
$scope module tb_adc_controller $end
$var wire 1 ! sample_and_hold $end
$var wire 12 " data [11:0] $end
$var wire 1 # dac_en $end
$var wire 12 $ dac [11:0] $end
$var wire 1 % comparator $end
$var wire 1 & ack $end
$var parameter 32 ' AVG_SHIFT $end
$var parameter 35 ( HALF_DIVISOR $end
$var parameter 32 ) NUM_SAMPLES $end
$var parameter 32 * OVERSAMPLE_BITS $end
$var parameter 32 + WIDTH $end
$var reg 16 , accumulator [15:0] $end
$var reg 12 - analog_input_equivalent [11:0] $end
$var reg 12 . averaged_result_round [11:0] $end
$var reg 12 / averaged_result_trunc [11:0] $end
$var reg 1 0 clk $end
$var reg 1 1 en_ $end
$var reg 12 2 first_result [11:0] $end
$var reg 3 3 noise [2:0] $end
$var reg 12 4 noisy_sample [11:0] $end
$var reg 14 5 oversampled_result [13:0] $end
$var reg 1 6 reset_ $end
$var reg 14 7 true_oversampled_value [13:0] $end
$var integer 32 8 seed [31:0] $end
$scope module u_dut $end
$var wire 1 0 clk $end
$var wire 1 % comparator $end
$var wire 1 # dac_en $end
$var wire 12 9 data [11:0] $end
$var wire 1 1 en_ $end
$var wire 1 6 reset_ $end
$var wire 12 : test_value [11:0] $end
$var wire 1 ! sample_and_hold $end
$var wire 1 ; is_final_bit $end
$var wire 12 < dac [11:0] $end
$var wire 1 & ack $end
$var parameter 2 = S_CONVERT $end
$var parameter 2 > S_FINISH $end
$var parameter 2 ? S_IDLE $end
$var parameter 2 @ S_INIT $end
$var parameter 32 A WIDTH $end
$var reg 12 B counter_reg [11:0] $end
$var reg 12 C dac_reg [11:0] $end
$var reg 12 D data_out_reg [11:0] $end
$var reg 2 E next_state [1:0] $end
$var reg 2 F state [1:0] $end
$upscope $end
$scope begin $ivl_for_loop0 $end
$var integer 32 G i [31:0] $end
$upscope $end
$scope begin $ivl_for_loop1 $end
$var integer 32 H i [31:0] $end
$upscope $end
$scope task get_random $end
$upscope $end
$upscope $end
$enddefinitions $end
$comment Show the parameter values. $end
$dumpall
b1100 A
b1 @
b0 ?
b11 >
b10 =
b1100 +
b10 *
b10000 )
b1000 (
b100 '
$end
#0
$dumpvars
bx H
bx G
b0 F
b0 E
b0 D
b0 C
b0 B
b0 <
0;
b0 :
b0 9
b10011000110 8
bx 7
06
bx 5
bx 4
bx 3
bx 2
11
00
bx /
bx .
bx -
bx ,
0&
x%
b0 $
0#
b0 "
0!
$end
#5000
10
#10000
00
#15000
10
#20000
16
00
#25000
10
#30000
b1 E
01
00
1%
b10101101101 -
b10110101101011000001010101101101 8
b0 G
#35000
b10 E
1#
1!
b1 F
10
#40000
00
#45000
0%
b100000000000 $
b100000000000 <
b100000000000 :
b100000000000 B
0!
b10 F
10
#50000
00
#55000
1%
b10000000000 $
b10000000000 <
b10000000000 :
b10000000000 B
10
#60000
00
#65000
0%
b11000000000 $
b11000000000 <
b11000000000 :
b1000000000 B
b10000000000 C
10
#70000
00
#75000
1%
b10100000000 $
b10100000000 <
b10100000000 :
b100000000 B
10
#80000
00
#85000
0%
b10110000000 $
b10110000000 <
b10110000000 :
b10000000 B
b10100000000 C
10
#90000
00
#95000
1%
b10101000000 $
b10101000000 <
b10101000000 :
b1000000 B
10
#100000
00
#105000
b10101100000 $
b10101100000 <
b10101100000 :
b100000 B
b10101000000 C
10
#110000
00
#115000
0%
b10101110000 $
b10101110000 <
b10101110000 :
b10000 B
b10101100000 C
10
#120000
00
#125000
1%
b10101101000 $
b10101101000 <
b10101101000 :
b1000 B
10
#130000
00
#135000
b10101101100 $
b10101101100 <
b10101101100 :
b100 B
b10101101000 C
10
#140000
00
#145000
0%
b10101101110 $
b10101101110 <
b10101101110 :
b10 B
b10101101100 C
10
#150000
00
#155000
b11 E
1%
b10101101101 $
b10101101101 <
1;
b10101101101 :
b1 B
10
#160000
00
#165000
11
0;
b0 E
0#
b10101101101 "
b10101101101 9
b10101101101 D
b0 B
b10101101101 C
1&
b11 F
10
#170000
00
#175000
0&
b0 F
10
#180000
00
#185000
10
#190000
00
#195000
10
#200000
00
#205000
10
#210000
00
#215000
b1 E
01
10
b11111101000 -
b11110010110100111011111101000 8
b1 G
#220000
00
#225000
b10 E
1#
1!
b1 F
10
#230000
00
#235000
0%
b100000000000 $
b100000000000 <
b100000000000 :
0!
b10 F
b100000000000 B
b0 C
10
#240000
00
#245000
1%
b10000000000 $
b10000000000 <
b10000000000 :
b10000000000 B
10
#250000
00
#255000
b11000000000 $
b11000000000 <
b11000000000 :
b1000000000 B
b10000000000 C
10
#260000
00
#265000
b11100000000 $
b11100000000 <
b11100000000 :
b100000000 B
b11000000000 C
10
#270000
00
#275000
b11110000000 $
b11110000000 <
b11110000000 :
b10000000 B
b11100000000 C
10
#280000
00
#285000
b11111000000 $
b11111000000 <
b11111000000 :
b1000000 B
b11110000000 C
10
#290000
00
#295000
b11111100000 $
b11111100000 <
b11111100000 :
b100000 B
b11111000000 C
10
#300000
00
#305000
0%
b11111110000 $
b11111110000 <
b11111110000 :
b10000 B
b11111100000 C
10
#310000
00
#315000
1%
b11111101000 $
b11111101000 <
b11111101000 :
b1000 B
10
#320000
00
#325000
0%
b11111101100 $
b11111101100 <
b11111101100 :
b100 B
b11111101000 C
10
#330000
00
#335000
b11111101010 $
b11111101010 <
b11111101010 :
b10 B
10
#340000
00
#345000
b11 E
b11111101001 $
b11111101001 <
1;
b11111101001 :
b1 B
10
#350000
00
#355000
11
b0 E
0#
1%
b11111101000 $
b11111101000 <
0;
b11111101000 :
1&
b11 F
b11111101000 "
b11111101000 9
b11111101000 D
b0 B
10
#360000
00
#365000
0&
b0 F
10
#370000
00
#375000
10
#380000
00
#385000
10
#390000
00
#395000
10
#400000
00
#405000
b1 E
01
10
b101000100111 -
b10001000011101010111101000100111 8
b10 G
#410000
00
#415000
b10 E
1#
1!
b1 F
10
#420000
00
#425000
b100000000000 $
b100000000000 <
b100000000000 :
b100000000000 B
b0 C
0!
b10 F
10
#430000
00
#435000
0%
b110000000000 $
b110000000000 <
b110000000000 :
b10000000000 B
b100000000000 C
10
#440000
00
#445000
1%
b101000000000 $
b101000000000 <
b101000000000 :
b1000000000 B
10
#450000
00
#455000
0%
b101100000000 $
b101100000000 <
b101100000000 :
b100000000 B
b101000000000 C
10
#460000
00
#465000
b101010000000 $
b101010000000 <
b101010000000 :
b10000000 B
10
#470000
00
#475000
b101001000000 $
b101001000000 <
b101001000000 :
b1000000 B
10
#480000
00
#485000
1%
b101000100000 $
b101000100000 <
b101000100000 :
b100000 B
10
#490000
00
#495000
0%
b101000110000 $
b101000110000 <
b101000110000 :
b10000 B
b101000100000 C
10
#500000
00
#505000
b101000101000 $
b101000101000 <
b101000101000 :
b1000 B
10
#510000
00
#515000
1%
b101000100100 $
b101000100100 <
b101000100100 :
b100 B
10
#520000
00
#525000
b101000100110 $
b101000100110 <
b101000100110 :
b10 B
b101000100100 C
10
#530000
00
#535000
b11 E
b101000100111 $
b101000100111 <
1;
b101000100111 :
b1 B
b101000100110 C
10
#540000
00
#545000
0;
b1 E
0%
b101011010 -
b11100110111000001011000101011010 8
b101000100111 2
0#
b101000100111 "
b101000100111 9
b101000100111 D
b0 B
b101000100111 C
1&
b11 F
10
#550000
00
#555000
b10 E
1#
1!
0&
b1 F
10
#560000
00
#565000
b100000000000 $
b100000000000 <
b100000000000 :
b100000000000 B
b0 C
0!
b10 F
10
#570000
00
#575000
b10000000000 $
b10000000000 <
b10000000000 :
b10000000000 B
10
#580000
00
#585000
b1000000000 $
b1000000000 <
b1000000000 :
b1000000000 B
10
#590000
00
#595000
1%
b100000000 $
b100000000 <
b100000000 :
b100000000 B
10
#600000
00
#605000
0%
b110000000 $
b110000000 <
b110000000 :
b10000000 B
b100000000 C
10
#610000
00
#615000
1%
b101000000 $
b101000000 <
b101000000 :
b1000000 B
10
#620000
00
#625000
0%
b101100000 $
b101100000 <
b101100000 :
b100000 B
b101000000 C
10
#630000
00
#635000
1%
b101010000 $
b101010000 <
b101010000 :
b10000 B
10
#640000
00
#645000
b101011000 $
b101011000 <
b101011000 :
b1000 B
b101010000 C
10
#650000
00
#655000
0%
b101011100 $
b101011100 <
b101011100 :
b100 B
b101011000 C
10
#660000
00
#665000
1%
b101011010 $
b101011010 <
b101011010 :
b10 B
10
#670000
00
#675000
b11 E
0%
b101011011 $
b101011011 <
1;
b101011011 :
b1 B
b101011010 C
10
#680000
00
#685000
11
0;
b101011010 :
b0 E
0#
1%
b101011010 $
b101011010 <
b101011010 "
b101011010 9
b101011010 D
b0 B
1&
b11 F
10
#690000
00
#695000
0&
b0 F
10
#700000
00
#705000
10
#710000
00
#715000
10
#720000
00
#725000
10
#730000
00
#735000
b1 E
01
10
b10001000010 -
b10001000010 4
b110 3
b0 H
b0 ,
b1000011110001 7
b1010011000100011001010110011100 8
#740000
00
#745000
b10 E
1#
1!
b1 F
10
#750000
00
#755000
0%
b100000000000 $
b100000000000 <
b100000000000 :
0!
b10 F
b100000000000 B
b0 C
10
#760000
00
#765000
1%
b10000000000 $
b10000000000 <
b10000000000 :
b10000000000 B
10
#770000
00
#775000
0%
b11000000000 $
b11000000000 <
b11000000000 :
b1000000000 B
b10000000000 C
10
#780000
00
#785000
b10100000000 $
b10100000000 <
b10100000000 :
b100000000 B
10
#790000
00
#795000
b10010000000 $
b10010000000 <
b10010000000 :
b10000000 B
10
#800000
00
#805000
1%
b10001000000 $
b10001000000 <
b10001000000 :
b1000000 B
10
#810000
00
#815000
0%
b10001100000 $
b10001100000 <
b10001100000 :
b100000 B
b10001000000 C
10
#820000
00
#825000
b10001010000 $
b10001010000 <
b10001010000 :
b10000 B
10
#830000
00
#835000
b10001001000 $
b10001001000 <
b10001001000 :
b1000 B
10
#840000
00
#845000
b10001000100 $
b10001000100 <
b10001000100 :
b100 B
10
#850000
00
#855000
1%
b10001000010 $
b10001000010 <
b10001000010 :
b10 B
10
#860000
00
#865000
b11 E
0%
b10001000011 $
b10001000011 <
1;
b10001000011 :
b1 B
b10001000010 C
10
#870000
00
#875000
b1 E
b10001000011 -
b10001000011 4
b111 3
b10010001010111011010001001011 8
b1 H
b10001000010 ,
0#
1%
b10001000010 $
b10001000010 <
0;
b10001000010 :
1&
b11 F
b10001000010 "
b10001000010 9
b10001000010 D
b0 B
10
#880000
00
#885000
b10 E
1#
1!
0&
b1 F
10
#890000
00
#895000
0%
b100000000000 $
b100000000000 <
b100000000000 :
0!
b10 F
b100000000000 B
b0 C
10
#900000
00
#905000
1%
b10000000000 $
b10000000000 <
b10000000000 :
b10000000000 B
10
#910000
00
#915000
0%
b11000000000 $
b11000000000 <
b11000000000 :
b1000000000 B
b10000000000 C
10
#920000
00
#925000
b10100000000 $
b10100000000 <
b10100000000 :
b100000000 B
10
#930000
00
#935000
b10010000000 $
b10010000000 <
b10010000000 :
b10000000 B
10
#940000
00
#945000
1%
b10001000000 $
b10001000000 <
b10001000000 :
b1000000 B
10
#950000
00
#955000
0%
b10001100000 $
b10001100000 <
b10001100000 :
b100000 B
b10001000000 C
10
#960000
00
#965000
b10001010000 $
b10001010000 <
b10001010000 :
b10000 B
10
#970000
00
#975000
b10001001000 $
b10001001000 <
b10001001000 :
b1000 B
10
#980000
00
#985000
b10001000100 $
b10001000100 <
b10001000100 :
b100 B
10
#990000
00
#995000
1%
b10001000010 $
b10001000010 <
b10001000010 :
b10 B
10
#1000000
00
#1005000
b11 E
b10001000011 $
b10001000011 <
1;
b10001000011 :
b1 B
b10001000010 C
10
#1010000
00
#1015000
b1 E
b111 3
b101101110011111111110100101110 8
b10 H
b100010000101 ,
0#
0;
1&
b11 F
b10001000011 "
b10001000011 9
b10001000011 D
b0 B
b10001000011 C
10
#1020000
00
#1025000
b10 E
1#
1!
0&
b1 F
10
#1030000
00
#1035000
0%
b100000000000 $
b100000000000 <
b100000000000 :
0!
b10 F
b100000000000 B
b0 C
10
#1040000
00
#1045000
1%
b10000000000 $
b10000000000 <
b10000000000 :
b10000000000 B
10
#1050000
00
#1055000
0%
b11000000000 $
b11000000000 <
b11000000000 :
b1000000000 B
b10000000000 C
10
#1060000
00
#1065000
b10100000000 $
b10100000000 <
b10100000000 :
b100000000 B
10
#1070000
00
#1075000
b10010000000 $
b10010000000 <
b10010000000 :
b10000000 B
10
#1080000
00
#1085000
1%
b10001000000 $
b10001000000 <
b10001000000 :
b1000000 B
10
#1090000
00
#1095000
0%
b10001100000 $
b10001100000 <
b10001100000 :
b100000 B
b10001000000 C
10
#1100000
00
#1105000
b10001010000 $
b10001010000 <
b10001010000 :
b10000 B
10
#1110000
00
#1115000
b10001001000 $
b10001001000 <
b10001001000 :
b1000 B
10
#1120000
00
#1125000
b10001000100 $
b10001000100 <
b10001000100 :
b100 B
10
#1130000
00
#1135000
1%
b10001000010 $
b10001000010 <
b10001000010 :
b10 B
10
#1140000
00
#1145000
b11 E
b10001000011 $
b10001000011 <
1;
b10001000011 :
b1 B
b10001000010 C
10
#1150000
00
#1155000
b1 E
0%
b10000111101 -
b10000111101 4
b1 3
b101000010111010010001010110101 8
b11 H
b110011001000 ,
0#
0;
1&
b11 F
b0 B
b10001000011 C
10
#1160000
00
#1165000
b10 E
1#
1!
0&
b1 F
10
#1170000
00
#1175000
b100000000000 $
b100000000000 <
b100000000000 :
0!
b10 F
b100000000000 B
b0 C
10
#1180000
00
#1185000
1%
b10000000000 $
b10000000000 <
b10000000000 :
b10000000000 B
10
#1190000
00
#1195000
0%
b11000000000 $
b11000000000 <
b11000000000 :
b1000000000 B
b10000000000 C
10
#1200000
00
#1205000
b10100000000 $
b10100000000 <
b10100000000 :
b100000000 B
10
#1210000
00
#1215000
b10010000000 $
b10010000000 <
b10010000000 :
b10000000 B
10
#1220000
00
#1225000
b10001000000 $
b10001000000 <
b10001000000 :
b1000000 B
10
#1230000
00
#1235000
1%
b10000100000 $
b10000100000 <
b10000100000 :
b100000 B
10
#1240000
00
#1245000
b10000110000 $
b10000110000 <
b10000110000 :
b10000 B
b10000100000 C
10
#1250000
00
#1255000
b10000111000 $
b10000111000 <
b10000111000 :
b1000 B
b10000110000 C
10
#1260000
00
#1265000
b10000111100 $
b10000111100 <
b10000111100 :
b100 B
b10000111000 C
10
#1270000
00
#1275000
0%
b10000111110 $
b10000111110 <
b10000111110 :
b10 B
b10000111100 C
10
#1280000
00
#1285000
b11 E
1%
b10000111101 $
b10000111101 <
1;
b10000111101 :
b1 B
10
#1290000
00
#1295000
b1 E
b10001000010 -
b10001000010 4
b110 3
b11001000101010101101010010010000 8
b100 H
b1000100000101 ,
0#
0;
1&
b11 F
b10000111101 "
b10000111101 9
b10000111101 D
b0 B
b10000111101 C
10
#1300000
00
#1305000
b10 E
1#
1!
0&
b1 F
10
#1310000
00
#1315000
0%
b100000000000 $
b100000000000 <
b100000000000 :
0!
b10 F
b100000000000 B
b0 C
10
#1320000
00
#1325000
1%
b10000000000 $
b10000000000 <
b10000000000 :
b10000000000 B
10
#1330000
00
#1335000
0%
b11000000000 $
b11000000000 <
b11000000000 :
b1000000000 B
b10000000000 C
10
#1340000
00
#1345000
b10100000000 $
b10100000000 <
b10100000000 :
b100000000 B
10
#1350000
00
#1355000
b10010000000 $
b10010000000 <
b10010000000 :
b10000000 B
10
#1360000
00
#1365000
1%
b10001000000 $
b10001000000 <
b10001000000 :
b1000000 B
10
#1370000
00
#1375000
0%
b10001100000 $
b10001100000 <
b10001100000 :
b100000 B
b10001000000 C
10
#1380000
00
#1385000
b10001010000 $
b10001010000 <
b10001010000 :
b10000 B
10
#1390000
00
#1395000
b10001001000 $
b10001001000 <
b10001001000 :
b1000 B
10
#1400000
00
#1405000
b10001000100 $
b10001000100 <
b10001000100 :
b100 B
10
#1410000
00
#1415000
1%
b10001000010 $
b10001000010 <
b10001000010 :
b10 B
10
#1420000
00
#1425000
b11 E
0%
b10001000011 $
b10001000011 <
1;
b10001000011 :
b1 B
b10001000010 C
10
#1430000
00
#1435000
b1 E
b10000111110 -
b10000111110 4
b10 3
b111111110111010001111010101111 8
b101 H
b1010101000111 ,
0#
0%
b10001000010 $
b10001000010 <
0;
b10001000010 :
1&
b11 F
b10001000010 "
b10001000010 9
b10001000010 D
b0 B
10
#1440000
00
#1445000
b10 E
1#
1!
0&
b1 F
10
#1450000
00
#1455000
b100000000000 $
b100000000000 <
b100000000000 :
0!
b10 F
b100000000000 B
b0 C
10
#1460000
00
#1465000
1%
b10000000000 $
b10000000000 <
b10000000000 :
b10000000000 B
10
#1470000
00
#1475000
0%
b11000000000 $
b11000000000 <
b11000000000 :
b1000000000 B
b10000000000 C
10
#1480000
00
#1485000
b10100000000 $
b10100000000 <
b10100000000 :
b100000000 B
10
#1490000
00
#1495000
b10010000000 $
b10010000000 <
b10010000000 :
b10000000 B
10
#1500000
00
#1505000
b10001000000 $
b10001000000 <
b10001000000 :
b1000000 B
10
#1510000
00
#1515000
1%
b10000100000 $
b10000100000 <
b10000100000 :
b100000 B
10
#1520000
00
